rio_ds_mask.py
rio_ds_mask-1.2.dist-info/DESCRIPTION.rst
rio_ds_mask-1.2.dist-info/METADATA
rio_ds_mask-1.2.dist-info/RECORD
rio_ds_mask-1.2.dist-info/WHEEL
rio_ds_mask-1.2.dist-info/entry_points.txt
rio_ds_mask-1.2.dist-info/metadata.json
rio_ds_mask-1.2.dist-info/top_level.txt
rio_ds_mask-1.2.dist-info/zip-safe
