Metadata-Version: 2.0
Name: rio-ds-mask
Version: 1.2
Summary: Extract an image's dataset-level mask and write to a new file.
Home-page: https://github.com/geowurster/rio-ds-mask
Author: Kevin Wurster
Author-email: wursterk@gmail.com
License: New BSD
Keywords: rasterio plugin dataset mask
Platform: UNKNOWN
Classifier: Development Status :: 5 - Production/Stable
Classifier: Intended Audience :: Developers
Classifier: Intended Audience :: Information Technology
Classifier: Intended Audience :: Science/Research
Classifier: License :: OSI Approved :: BSD License
Classifier: Programming Language :: Python :: 2
Classifier: Programming Language :: Python :: 3
Classifier: Topic :: Multimedia :: Graphics :: Graphics Conversion
Classifier: Topic :: Scientific/Engineering :: GIS
Requires-Dist: click
Requires-Dist: cligj
Requires-Dist: rasterio (>=0.36.0)
Provides-Extra: all
Requires-Dist: pytest (>=3); extra == 'all'
Requires-Dist: pytest-cov; extra == 'all'
Requires-Dist: coveralls; extra == 'all'
Provides-Extra: test
Requires-Dist: pytest (>=3); extra == 'test'
Requires-Dist: pytest-cov; extra == 'test'
Requires-Dist: coveralls; extra == 'test'
